niquests_negotiate_sspi/__init__.py
niquests_negotiate_sspi/__init__.pyi
niquests_negotiate_sspi/niquests_negotiate_sspi.py
niquests_negotiate_sspi/niquests_negotiate_sspi.pyi
niquests_negotiate_sspi-0.6.1.dist-info/METADATA
niquests_negotiate_sspi-0.6.1.dist-info/WHEEL
niquests_negotiate_sspi-0.6.1.dist-info/licenses/LICENSE.txt
niquests_negotiate_sspi-0.6.1.dist-info/RECORD
