Metadata-Version: 2.4
Name: niquests-negotiate-sspi
Version: 0.6.1
Summary: This package allows for Single-Sign On HTTP Negotiate authentication using the niquests library on Windows.
Author-email: Brandon Davidson <brad@oatmail.org>
Maintainer: NaruZosa
License:    Copyright 2016 Brandon Davidson
License-File: LICENSE.txt
Classifier: Development Status :: 4 - Beta
Classifier: Environment :: Win32 (MS Windows)
Classifier: Intended Audience :: Developers
Classifier: License :: OSI Approved :: Apache Software License
Classifier: Programming Language :: Python
Classifier: Programming Language :: Python :: 3.7
Classifier: Programming Language :: Python :: 3.8
Classifier: Programming Language :: Python :: 3.9
Classifier: Programming Language :: Python :: 3.10
Classifier: Programming Language :: Python :: 3.11
Classifier: Programming Language :: Python :: 3.12
Classifier: Programming Language :: Python :: 3.13
Requires-Python: >=3.7
Requires-Dist: niquests>=3.14.1
Requires-Dist: pywin32>=223
Requires-Dist: urllib3-future>=2.13.900
